client/__init__.py
client/client_app.py
client/client/__init__.py
client/client/client_db.py
client/client/dialog_add_contact.py
client/client/dialog_del_contact.py
client/client/dialog_start.py
client/client/main_window.py
client/client/main_window_ui.py
client/client/transport.py
client/common/__init__.py
client/common/decos.py
client/common/descrptrs.py
client/common/errors.py
client/common/metaclasses.py
client/common/utils.py
client/common/variables.py
client/log/__init__.py
client/log/client_log_config.py
client/log/server_log_config.py
client/unit_tests/__init__.py
client/unit_tests/test_client.py
client/unit_tests/test_server.py
client/unit_tests/test_utils.py
Bel_messenger_client-0.1.0.dist-info/METADATA
Bel_messenger_client-0.1.0.dist-info/WHEEL
Bel_messenger_client-0.1.0.dist-info/top_level.txt
Bel_messenger_client-0.1.0.dist-info/RECORD
