Metadata-Version: 2.1
Name: Bel-messenger-client
Version: 0.1.0
Summary: Bel_messenger. Client_app
Home-page: UNKNOWN
Author: Sergey Sukhanov
Author-email: sergey.bv26@gmail.com
License: UNKNOWN
Platform: UNKNOWN
Requires-Dist: PyQt5
Requires-Dist: sqlalchemy
Requires-Dist: pycryptodome
Requires-Dist: pycryptodomex
